{
  "stable_id": "POL-0104",
  "family": {
    "category": "F-POL",
    "subcategory": "F-POL-polymer-pp",
    "alloy_base": "F-AB-polypropylene-homopolymer",
    "element_families": []
  },
  "legacy_id": "R_0194",
  "origin": "reference(supplementary)",
  "id": "R_0194",
  "name": "Polypropylene (homopolymer)",
  "category": "Polymer",
  "subcategory": "Polymer - PP",
  "tier": "reference",
  "manufacturers": [
    "Reference data"
  ],
  "machines": [],
  "processes": [
    "Injection Molding"
  ],
  "heat_treatment": null,
  "ranges": {
    "density": {
      "min": 0.905,
      "max": 0.905,
      "typical": 0.905,
      "n": 2,
      "confidence": "handbook"
    },
    "yield_strength": {
      "min": 28,
      "max": 32,
      "typical": 32,
      "n": 2,
      "confidence": "handbook"
    },
    "uts": {
      "min": 32,
      "max": 35,
      "typical": 35,
      "n": 2,
      "confidence": "handbook"
    },
    "elongation": {
      "min": 50,
      "max": 150,
      "typical": 150,
      "n": 2,
      "confidence": "handbook"
    },
    "modulus": {
      "min": 1.3,
      "max": 1.4,
      "typical": 1.4,
      "n": 2,
      "confidence": "handbook"
    },
    "hardness": null,
    "thermal_conductivity": {
      "min": 0.12,
      "max": 0.12,
      "typical": 0.12,
      "n": 2,
      "confidence": "handbook"
    },
    "fatigue_strength": null,
    "impact_strength": null,
    "electrical_conductivity": {
      "min": 0,
      "max": 0,
      "typical": 0,
      "n": 0,
      "estimated": true,
      "confidence": "class",
      "provenance": "class:Polymer - PP (FDM)"
    },
    "max_service_temp": {
      "min": 50,
      "max": 150,
      "typical": 100,
      "n": 0,
      "estimated": true,
      "confidence": "class",
      "provenance": "class:Polymer - PP (FDM)"
    },
    "thermal_expansion": {
      "min": 40,
      "max": 120,
      "typical": 80,
      "n": 0,
      "estimated": true,
      "confidence": "class",
      "provenance": "class:Polymer - PP (FDM)"
    },
    "poisson_ratio": {
      "min": 0.2,
      "max": 0.6,
      "typical": 0.4,
      "n": 0,
      "estimated": true,
      "confidence": "class",
      "provenance": "class:Polymer - PP (FDM)"
    },
    "specific_heat": {
      "min": 750,
      "max": 2250,
      "typical": 1500,
      "n": 0,
      "estimated": true,
      "confidence": "class",
      "provenance": "class:Polymer - PP (FDM)"
    },
    "glass_transition_temp": {
      "min": -15,
      "max": -5,
      "typical": -10,
      "n": 0,
      "estimated": true,
      "confidence": "class",
      "provenance": "class:Polymer - PP (FDM)"
    },
    "price_per_kg": {
      "min": 12.5,
      "max": 37.5,
      "typical": 25,
      "n": 0,
      "estimated": true,
      "confidence": "class",
      "provenance": "class:Polymer - PP (FDM)"
    },
    "price_per_cm3": {
      "min": 0.0113,
      "max": 0.0339,
      "typical": 0.0226,
      "n": 0,
      "estimated": true,
      "confidence": "class",
      "provenance": "class:Polymer - PP (FDM)"
    },
    "delivered_price_per_kg": {
      "min": 25,
      "max": 25,
      "typical": 25,
      "n": 0,
      "estimated": true,
      "confidence": "derived"
    }
  },
  "composition": {
    "C": "85.6",
    "H": "14.4"
  },
  "sources": [
    {
      "label": "MatWeb — Polypropylene (PP)",
      "url": "https://www.matweb.com/search/QuickText.aspx?SearchText=Polypropylene",
      "verified": false
    },
    {
      "label": "Material datasheets — polypropylene homopolymer",
      "url": null,
      "verified": false
    },
    {
      "label": "ExxonMobil PP product family",
      "url": "https://www.exxonmobilchemical.com/en/products/polymers",
      "verified": true
    },
    {
      "label": "SABIC PP resin technical guide",
      "url": "https://www.sabic.com/en/products/polymers/polypropylene-pp",
      "verified": true
    },
    {
      "label": "MatWeb — Polypropylene Homopolymer",
      "url": "https://www.matweb.com/search/DataSheet.aspx?MatGUID=e7e3e89ab5ab441b8e7a8c8e0b7c3e6e",
      "verified": false
    }
  ],
  "points": [
    [
      0.905,
      32,
      35,
      150,
      1.4,
      0,
      0.12
    ],
    [
      0.905,
      28,
      32,
      50,
      1.3,
      0,
      0.12
    ]
  ],
  "machinability": "Good",
  "weldability": "Thermoplastic",
  "corrosion_resistance": "Excellent",
  "industry_note": "Polypropylene (PP). Homopolymer vs Random Copolymer (RCP) vs Block Copolymer (BCP). Tg ≈ -10°C (cold-brittle), Tm 160-170°C, HDT (0.46 MPa) ≈ 100°C, max service 100-120°C. Homo: σy 33-38 / UTS 35-40 / El 100-600% / E 1.4-1.6 GPa / ρ 0.90 g/cc (가장 가벼운 thermoplastic). 화학 약품 저항 우수 (산/알칼리). 자동차 bumper (BCP), 마이크로파 ware, 식품 용기, 의료 disposable (주사기, IV 백). 저온 충격 약점 → BCP 또는 EPDM 첨가.",
  "meta": {
    "reference": true,
    "flame_ul94": "HB",
    "uv_resistance": "Poor",
    "moisture_24h": 0.02,
    "polymer": true,
    "_r173_note_applied": true
  },
  "density": 0.905,
  "yield_strength": 32,
  "uts": 35,
  "elongation": 150,
  "modulus": 1.4,
  "hardness": null,
  "thermal_conductivity": 0.12,
  "fatigue_strength": null,
  "impact_strength": null,
  "manufacturer": "Reference data",
  "process": "Injection Molding",
  "source": "MatWeb — Polypropylene (PP)",
  "aliases": [],
  "families": [
    "Polymer",
    "Polymer - PP (FDM)"
  ],
  "electrical_conductivity": 0,
  "max_service_temp": 100,
  "thermal_expansion": 80,
  "poisson_ratio": 0.4,
  "specific_heat": 1500,
  "glass_transition_temp": -10,
  "price_per_kg": 25,
  "price_per_cm3": 0.0226,
  "popularity": 5,
  "machining_cost_factor": 0.7,
  "ht_cost_factor": 1,
  "price_condition_factor": 1,
  "price_form_factor": 1,
  "price_grade_premium": 1,
  "delivered_price_per_kg": 25,
  "total_cost_estimate": 17.5,
  "min_wall_thickness": 0.8,
  "surface_finish_typical": 1.6,
  "tolerance_class": "IT10-12",
  "rohs_compliant": true,
  "story": "Polypropylene (PP) 의 합성은 1954년 이탈리아 Politecnico di Milano 의 Giulio Natta 가 발견했어요. 그는 독일 Karl Ziegler 의 1953년 Ziegler catalyst (TiCl₃ + AlR₃) 를 이용해 propylene 을 isotactic 한 stereoregular polymer 로 만드는 데 성공했고, 이게 1963년 두 사람의 Nobel Chemistry Prize 의 핵심 업적이 됐죠. Natta 의 발견 이후 1957년 이탈리아 Montecatini 가 'Moplen' 이라는 trade name 으로 PP 상품화를 시작했습니다.\n\nPP 의 매력은 commodity polymer 중에서 가장 가벼움 (밀도 0.9 g/cm³, water 보다 가벼움 — only commodity polymer that floats) + chemical resistance + low cost ($1.2-2/kg) 의 조합입니다. Tm 165°C · Tg -10°C · σy 30-40 MPa. 1957년 이후 전 세계 plastic 생산의 두 번째로 큰 polymer (PE 가 1위).\n\n응용은 commodity 자체입니다. 식품 포장 (yogurt cup, deli container — heat-sealable + 식품 contact 안전), 자동차 bumper (대부분 신차 의 outer bumper 가 PP-EPDM blend), 의류 carpet fiber (commercial carpet 의 30%), 의료 syringe + IV bag, hot-water pipe (PP-RC, random copolymer), 가전 dishwasher inner tub, 그리고 'living hinge' (단일 부품의 lid hinge — 1956년 발견된 PP 의 unique 특성). 환경 측면: PP 는 결정 + amorphous 부분이 모두 재활용 가능하지만 회수 비율은 PET 보다 낮습니다 (소비자 분리수거의 어려움).",
  "story_refs": [
    "Natta G (1955) \"Macromolecules with Stereospecific Structure\", J Am Chem Soc 77",
    "Karger-Kocsis J (ed., 1995) Polypropylene Structure, Blends and Composites, Chapman & Hall",
    "Maier C & Calafut T (1998) Polypropylene: The Definitive User's Guide and Databook, William Andrew"
  ],
  "confidence_tier": "high"
}
