{
  "stable_id": "MET-0384",
  "family": {
    "category": "F-MET",
    "subcategory": "F-MET-copper-alloy",
    "alloy_base": "F-AB-c21000-red-brass-95cu-5zn-gilding-metal",
    "element_families": [
      "F-EL-copper-based"
    ]
  },
  "legacy_id": "R_0285_2",
  "origin": "reference(supplementary)",
  "id": "R_0285_2",
  "name": "C21000 (Red Brass 95Cu-5Zn, Gilding Metal) — 1/2H",
  "category": "Metal",
  "subcategory": "Copper Alloy",
  "tier": "reference",
  "manufacturers": [
    "Reference data"
  ],
  "machines": [],
  "processes": [
    "Wrought (cold-rolled strip)"
  ],
  "heat_treatment": "1/2H",
  "ranges": {
    "density": {
      "min": 8.86,
      "max": 8.86,
      "typical": 8.86,
      "n": 1,
      "confidence": "handbook"
    },
    "yield_strength": {
      "min": 270,
      "max": 270,
      "typical": 270,
      "n": 1,
      "confidence": "handbook"
    },
    "uts": {
      "min": 320,
      "max": 320,
      "typical": 320,
      "n": 1,
      "confidence": "handbook"
    },
    "elongation": {
      "min": 15,
      "max": 15,
      "typical": 15,
      "n": 1,
      "confidence": "handbook"
    },
    "modulus": {
      "min": 117,
      "max": 117,
      "typical": 117,
      "n": 1,
      "confidence": "handbook"
    },
    "hardness": {
      "min": 105,
      "max": 105,
      "typical": 105,
      "n": 1,
      "confidence": "handbook"
    },
    "thermal_conductivity": {
      "min": 234,
      "max": 234,
      "typical": 234,
      "n": 1,
      "confidence": "handbook"
    },
    "fatigue_strength": {
      "min": 70,
      "max": 130,
      "typical": 95,
      "n": 0,
      "confidence": "handbook",
      "provenance": "family:σf≈0.35·σy (ASM Vol.2 Cu alloys)"
    },
    "impact_strength": null,
    "fracture_toughness": {
      "min": 40,
      "max": 75,
      "typical": 55,
      "n": 0,
      "confidence": "class",
      "provenance": "class:Copper.org Brass"
    },
    "max_service_temp": {
      "typical": 200,
      "min": 150,
      "max": 250,
      "confidence": "handbook",
      "n": 1
    }
  },
  "composition": {
    "Cu": "94~96",
    "Zn": "balance",
    "Pb": "≤0.05",
    "Fe": "≤0.05"
  },
  "sources": [
    {
      "label": "Datasheet 3",
      "url": "https://www.poongsan.co.kr/eng/business/",
      "verified": true
    },
    {
      "label": "KIC fallback: Copper.org Brass",
      "url": null,
      "verified": false
    },
    {
      "label": "Fatigue fallback: σf ≈ 0.35·σy (ASM Vol.2 Cu alloys)",
      "url": null,
      "verified": false
    },
    {
      "label": "Copper Development Association — Red Brass family",
      "url": "https://www.copper.org/",
      "verified": false
    },
    {
      "label": "ASTM B36 — Brass Plate, Sheet, Strip, Rolled Bar",
      "url": "https://store.astm.org/b0036_b0036m-18.html",
      "verified": false
    }
  ],
  "points": [
    [
      8.86,
      270,
      320,
      15,
      117,
      105,
      234
    ]
  ],
  "machinability": "Good",
  "weldability": "Good",
  "corrosion_resistance": "Good",
  "industry_note": "Red Brass family (Cu-Zn, lower Zn = redder color, higher corrosion resistance): • C21000 (Gilding Metal, 95Cu-5Zn): O σy 80 / UTS 235 / El 45 — coinage (penny core), bullet jacket, decorative • C22000 (Commercial Bronze, 90Cu-10Zn): O σy 85 / UTS 255 / El 45 — costume jewelry, marine hardware • C23000 (Red Brass, 85Cu-15Zn): O σy 90 / UTS 270 / El 45 — plumbing fitting, heat exchanger tube Work-Tmax 200°C.",
  "meta": {
    "reference": true,
    "condition": "1/2H",
    "_r173_note_applied": true,
    "specs": [
      {
        "id": "ASTM B36",
        "org": "ASTM"
      }
    ]
  },
  "fracture_toughness": 55,
  "fatigue_strength": 95,
  "density": 8.86,
  "yield_strength": 270,
  "uts": 320,
  "elongation": 15,
  "modulus": 117,
  "hardness": 105,
  "thermal_conductivity": 234,
  "impact_strength": null,
  "manufacturer": "Reference data",
  "process": "Wrought (cold-rolled strip)",
  "source": "Datasheet 3",
  "aliases": [
    "Red Brass 95Cu-5Zn",
    "C2100"
  ],
  "families": [
    "Metal",
    "Copper Alloy"
  ],
  "popularity": 4.15,
  "machining_cost_factor": 0.5,
  "ht_cost_factor": 1.1,
  "price_condition_factor": 1.08,
  "price_form_factor": 1.2,
  "price_grade_premium": 1,
  "tolerance_class": "IT10-12",
  "rohs_compliant": true,
  "story": "C21000 (UNS C21000) 은 Cu-5% Zn 합금으로, 보통 '95-5 gilding metal' 이라고 부릅니다. 이름 그대로 도금처럼 보이는 황금빛 색조 때문에 1820년대부터 영국에서 fashion jewelry · 단추 · medallion 에 쓰여왔어요. Zn 함량이 낮아 brass 보다 Cu 가 더 우세한 합금이라 색상이 옅은 노란-금색이고 가공성도 OFHC copper 와 거의 동일합니다.\n\n현대 응용: 군 탄피 (.22 LR cartridge case 외피의 gilding 코팅), 1909년 이후 미국 1 cent coin 의 외피 (zinc core 위에 C21000 코팅), 일본·한국 의 1엔·10원 동전, 메달·기념패의 도금 base, 그리고 architectural decoration (문 손잡이, 동상). σy 70 MPa annealed → 480 MPa half-hard 까지 cold-work 으로 강화 가능하지만 보통은 annealed 상태로 spinning / coining 됩니다.\n\n흥미로운 사실은 1864년 미국 남북전쟁 당시 cartridge case 재료 부족으로 C21000 spinning 공정이 발달했고, 이게 현대 brass cartridge case 산업의 시작이 됐다는 점입니다. UNS 번호 'C2' 로 시작하는 Cu-Zn 계열 중 Zn 함량이 가장 낮아 'pre-brass' 또는 'red brass' 라고도 불러요.",
  "story_refs": [
    "ASTM B36 \"Standard Specification for Brass Plate, Sheet, Strip, and Rolled Bar\"",
    "Davis J R (2001) ASM Specialty Handbook: Copper and Copper Alloys",
    "Copper Development Association \"Standards Handbook: Wrought Copper Alloy Designations\""
  ],
  "confidence_tier": "medium",
  "_corrections": {
    "aliases": {
      "from": [
        "Red Brass 95Cu-5Zn"
      ]
    }
  }
}
